{
  "header": {
    "icon": {
      "color": "primary",
      "style": "circle",
      "name": "chat"
    },
    "color": "primary",
    "nav": [
      {
        "href": "",
        "label": "Home"
      },
      {
        "href": "about",
        "label": "About"
      },
      {
        "href": "posts",
        "label": "Blog"
      }
    ]
  },
  "footer": {
    "color": "primary",
    "social": {
      "facebook": "/",
      "twitter": "/",
      "instagram": "/"
    }
  },
  "theme": {
    "color": "purple",
    "font": "lato",
    "icon": "boxicon",
    "darkMode": "dark"
  }
}